arbitor/__init__.py
arbitor-0.1.5.dist-info/DESCRIPTION.rst
arbitor-0.1.5.dist-info/METADATA
arbitor-0.1.5.dist-info/metadata.json
arbitor-0.1.5.dist-info/RECORD
arbitor-0.1.5.dist-info/top_level.txt
arbitor-0.1.5.dist-info/WHEEL
