Metadata-Version: 2.0
Name: arbitor
Version: 0.1.5
Summary: UNKNOWN
Home-page: https://github.com/eleme/arbitor
Author: Haochuan Guo
Author-email: guohaochuan@gmail.com
License: BSD
Keywords: etcd
Platform: UNKNOWN
Requires-Dist: python-etcd
